ardu_acqua_visual-0.2.1.dist-info/DESCRIPTION.rst
ardu_acqua_visual-0.2.1.dist-info/METADATA
ardu_acqua_visual-0.2.1.dist-info/RECORD
ardu_acqua_visual-0.2.1.dist-info/WHEEL
ardu_acqua_visual-0.2.1.dist-info/metadata.json
ardu_acqua_visual-0.2.1.dist-info/top_level.txt
libacquavisual/__init__.py
libacquavisual/glassofwater.py
libacquavisual/hygrometer.py
libacquavisual/thermometer.py
