Metadata-Version: 2.0
Name: ardu-acqua-visual
Version: 0.2.1
Summary: Get sensor data over the serial line and draw some nice 3d objects.
Home-page: https://github.com/inofix/ardu-acqua-visual
Author: Michael Lustenberger
Author-email: mic@inofix.ch
License: GPLv3
Keywords: arduino sensor 3d serial
Platform: UNKNOWN
Classifier: Development Status :: 4 - Beta
Classifier: Intended Audience :: Developers
Classifier: Topic :: Scientific/Engineering
Classifier: Topic :: Internet
Classifier: Topic :: Software Development :: Libraries :: Python Modules
Classifier: License :: OSI Approved :: GNU General Public License (GPL)
Classifier: Programming Language :: Python :: 2
Classifier: Programming Language :: Python :: 2.7
Requires-Dist: ardu-report-lib
Requires-Dist: configargparse
